mansour_utils/__init__.py
mansour_utils/__main__.py
mansour_utils/timer.py
mansour_utils-0.2.2.dist-info/LICENSE.txt
mansour_utils-0.2.2.dist-info/METADATA
mansour_utils-0.2.2.dist-info/WHEEL
mansour_utils-0.2.2.dist-info/entry_points.txt
mansour_utils-0.2.2.dist-info/top_level.txt
mansour_utils-0.2.2.dist-info/RECORD
