Metadata-Version: 2.1
Name: mansour-utils
Version: 0.2.2
Summary: Mansour Mahboubi's tools
Author-email: Mansour Mahboubi <mansourmahboubi@outlook.com>
Project-URL: Homepage, https://github.com/mansourmahboubi/
Keywords: mansour
Classifier: License :: OSI Approved :: GNU General Public License v3 (GPLv3)
Classifier: Programming Language :: Python
Classifier: Programming Language :: Python :: 3
Requires-Python: >=3.8
License-File: LICENSE.txt
Provides-Extra: dev
Requires-Dist: black ; extra == 'dev'
Requires-Dist: pytest ; extra == 'dev'
